[
    {
        "calculationDate": "20230205",
        "outstanding": 848.4
    },
    {
        "calculationDate": "20220412",
        "outstanding": 0.0
    },
    {
        "calculationDate": "20220829",
        "outstanding": 0.0
    },
    {
        "calculationDate": "20220420",
        "outstanding": 2850.0
    },
    {
        "calculationDate": "20220903",
        "outstanding": 1655.0
    },
    {
        "calculationDate": "20220227",
        "outstanding": 83.0
    },
    {
        "calculationDate": "20221005",
        "outstanding": 429.0
    },
    {
        "calculationDate": "20220623",
        "outstanding": 0.0
    },
    {
        "calculationDate": "20230513",
        "outstanding": 4060.82
    },
    {
        "calculationDate": "20221002",
        "outstanding": 4206.0
    },
    {
        "calculationDate": "20220711",
        "outstanding": 0.0
    },
    {
        "calculationDate": "20220930",
        "outstanding": 4356.0
    },
    {
        "calculationDate": "20220215",
        "outstanding": 0.0
    },
    {
        "calculationDate": "20220609",
        "outstanding": 0.0
    },
    {
        "calculationDate": "20220909",
        "outstanding": 0.0
    },
    {
        "calculationDate": "20220406",
        "outstanding": 2265.0
    },
    {
        "calculationDate": "20220309",
        "outstanding": 4049.0
    },
    {
        "calculationDate": "20221008",
        "outstanding": 229.0
    },
    {
        "calculationDate": "20220807",
        "outstanding": 0.0
    },
    {
        "calculationDate": "20220303",
        "outstanding": 0.0
    },
    {
        "calculationDate": "20220313",
        "outstanding": 0.0
    },
    {
        "calculationDate": "20220301",
        "outstanding": 0.0
    },
    {
        "calculationDate": "20220806",
        "outstanding": 0.0
    },
    {
        "calculationDate": "20220512",
        "outstanding": 0.0
    },
    {
        "calculationDate": "20220213",
        "outstanding": 0.0
    },
    {
        "calculationDate": "20220803",
        "outstanding": 0.0
    },
    {
        "calculationDate": "20220327",
        "outstanding": 950.0
    },
    {
        "calculationDate": "20220918",
        "outstanding": 8356.0
    },
    {
        "calculationDate": "20221010",
        "outstanding": 587.0
    },
    {
        "calculationDate": "20221029",
        "outstanding": 2580.0
    },
    {
        "calculationDate": "20220418",
        "outstanding": 2683.0
    },
    {
        "calculationDate": "20220506",
        "outstanding": 3115.0
    },
    {
        "calculationDate": "20220916",
        "outstanding": 3396.0
    },
    {
        "calculationDate": "20220502",
        "outstanding": 0.0
    },
    {
        "calculationDate": "20220705",
        "outstanding": 2394.0
    },
    {
        "calculationDate": "20220910",
        "outstanding": 0.0
    },
    {
        "calculationDate": "20220410",
        "outstanding": 446.0
    },
    {
        "calculationDate": "20220908",
        "outstanding": 3240.0
    },
    {
        "calculationDate": "20221006",
        "outstanding": 0.0
    },
    {
        "calculationDate": "20220621",
        "outstanding": 0.0
    },
    {
        "calculationDate": "20220804",
        "outstanding": 655.0
    },
    {
        "calculationDate": "20221004",
        "outstanding": 5862.0
    },
    {
        "calculationDate": "20220311",
        "outstanding": 0.0
    },
    {
        "calculationDate": "20220414",
        "outstanding": 0.0
    },
    {
        "calculationDate": "20220601",
        "outstanding": 0.0
    },
    {
        "calculationDate": "20220827",
        "outstanding": 0.0
    },
    {
        "calculationDate": "20220701",
        "outstanding": 1818.0
    },
    {
        "calculationDate": "20220329",
        "outstanding": 3399.0
    },
    {
        "calculationDate": "20220801",
        "outstanding": 978.0
    },
    {
        "calculationDate": "20220607",
        "outstanding": 0.0
    },
    {
        "calculationDate": "20221027",
        "outstanding": 2580.0
    },
    {
        "calculationDate": "20221015",
        "outstanding": 3000.0
    },
    {
        "calculationDate": "20220805",
        "outstanding": 2089.0
    },
    {
        "calculationDate": "20220211",
        "outstanding": 0.0
    },
    {
        "calculationDate": "20220402",
        "outstanding": 3249.0
    },
    {
        "calculationDate": "20220707",
        "outstanding": 2864.0
    },
    {
        "calculationDate": "20220209",
        "outstanding": 0.0
    },
    {
        "calculationDate": "20220305",
        "outstanding": 0.0
    },
    {
        "calculationDate": "20220307",
        "outstanding": 769.0
    },
    {
        "calculationDate": "20220919",
        "outstanding": 8356.0
    },
    {
        "calculationDate": "20220730",
        "outstanding": 978.0
    },
    {
        "calculationDate": "20220223",
        "outstanding": 0.0
    }
]