[
    {
        "calculationDate": "20191230",
        "outstanding": 121527.0
    },
    {
        "calculationDate": "20180401",
        "outstanding": 105415.0
    },
    {
        "calculationDate": "20190213",
        "outstanding": 121497.0
    },
    {
        "calculationDate": "20180618",
        "outstanding": 119875.0
    },
    {
        "calculationDate": "20200820",
        "outstanding": 3000.0
    },
    {
        "calculationDate": "20190909",
        "outstanding": 111783.0
    },
    {
        "calculationDate": "20190826",
        "outstanding": 107990.0
    },
    {
        "calculationDate": "20170511",
        "outstanding": 18401.0
    },
    {
        "calculationDate": "20181129",
        "outstanding": 124663.0
    },
    {
        "calculationDate": "20190325",
        "outstanding": 120452.0
    },
    {
        "calculationDate": "20201207",
        "outstanding": 0.0
    },
    {
        "calculationDate": "20170821",
        "outstanding": 17390.0
    },
    {
        "calculationDate": "20200928",
        "outstanding": 50000.0
    },
    {
        "calculationDate": "20171113",
        "outstanding": 0.0
    },
    {
        "calculationDate": "20180516",
        "outstanding": 26976.0
    },
    {
        "calculationDate": "20170727",
        "outstanding": 85756.0
    },
    {
        "calculationDate": "20201126",
        "outstanding": 0.0
    },
    {
        "calculationDate": "20190405",
        "outstanding": 102181.0
    },
    {
        "calculationDate": "20180827",
        "outstanding": 43166.0
    },
    {
        "calculationDate": "20181029",
        "outstanding": 124014.0
    },
    {
        "calculationDate": "20190128",
        "outstanding": 124245.0
    },
    {
        "calculationDate": "20180712",
        "outstanding": 96073.0
    },
    {
        "calculationDate": "20190425",
        "outstanding": 0.0
    },
    {
        "calculationDate": "20190926",
        "outstanding": 109461.0
    },
    {
        "calculationDate": "20170828",
        "outstanding": 22890.0
    },
    {
        "calculationDate": "20200723",
        "outstanding": 44544.0
    },
    {
        "calculationDate": "20201106",
        "outstanding": 0.0
    },
    {
        "calculationDate": "20190729",
        "outstanding": 92006.0
    },
    {
        "calculationDate": "20180301",
        "outstanding": 74085.0
    },
    {
        "calculationDate": "20201102",
        "outstanding": 49120.0
    },
    {
        "calculationDate": "20191130",
        "outstanding": 105177.0
    },
    {
        "calculationDate": "20170413",
        "outstanding": 18461.0
    },
    {
        "calculationDate": "20171225",
        "outstanding": 0.0
    },
    {
        "calculationDate": "20200702",
        "outstanding": 41009.0
    },
    {
        "calculationDate": "20190308",
        "outstanding": 105736.0
    },
    {
        "calculationDate": "20170612",
        "outstanding": 62221.0
    },
    {
        "calculationDate": "20191031",
        "outstanding": 149931.0
    },
    {
        "calculationDate": "20190225",
        "outstanding": 116020.0
    },
    {
        "calculationDate": "20190604",
        "outstanding": 102950.0
    },
    {
        "calculationDate": "20180212",
        "outstanding": 29719.0
    },
    {
        "calculationDate": "20180517",
        "outstanding": 30886.0
    },
    {
        "outstanding": 112347.0
    },
    {
        "calculationDate": "20200504",
        "outstanding": 44816.0
    },
    {
        "calculationDate": "20200622",
        "outstanding": 40042.0
    },
    {
        "calculationDate": "20180809",
        "outstanding": 112017.0
    },
    {
        "calculationDate": "20190930",
        "outstanding": 139461.0
    },
    {
        "calculationDate": "20180927",
        "outstanding": 122107.0
    },
    {
        "calculationDate": "20180208",
        "outstanding": 59.0
    },
    {
        "calculationDate": "20171123",
        "outstanding": 0.0
    },
    {
        "calculationDate": "20170615",
        "outstanding": 64893.0
    },
    {
        "calculationDate": "20201026",
        "outstanding": 49120.0
    },
    {
        "calculationDate": "20200803",
        "outstanding": 23431.0
    },
    {
        "calculationDate": "20181119",
        "outstanding": 123856.0
    },
    {
        "calculationDate": "20200406",
        "outstanding": 90826.0
    },
    {
        "calculationDate": "20180706",
        "outstanding": 94875.0
    },
    {
        "calculationDate": "20191007",
        "outstanding": 111931.0
    },
    {
        "calculationDate": "20180925",
        "outstanding": 119591.0
    },
    {
        "calculationDate": "20180424",
        "outstanding": 111466.0
    },
    {
        "calculationDate": "20190311",
        "outstanding": 107153.0
    },
    {
        "calculationDate": "20190409",
        "outstanding": 109401.0
    },
    {
        "calculationDate": "20170627",
        "outstanding": 76099.0
    },
    {
        "calculationDate": "20200102",
        "outstanding": 149556.0
    },
    {
        "calculationDate": "20200713",
        "outstanding": 34544.0
    },
    {
        "calculationDate": "20171218",
        "outstanding": 760.0
    },
    {
        "calculationDate": "20170904",
        "outstanding": 38626.0
    },
    {
        "calculationDate": "20190301",
        "outstanding": 121481.0
    },
    {
        "calculationDate": "20200106",
        "outstanding": 105644.0
    },
    {
        "calculationDate": "20200305",
        "outstanding": 149208.0
    },
    {
        "calculationDate": "20190314",
        "outstanding": 117153.0
    },
    {
        "calculationDate": "20180510",
        "outstanding": 0.0
    },
    {
        "calculationDate": "20170410",
        "outstanding": 0.0
    },
    {
        "calculationDate": "20190905",
        "outstanding": 110761.0
    },
    {
        "calculationDate": "20190226",
        "outstanding": 116481.0
    },
    {
        "calculationDate": "20180528",
        "outstanding": 62090.0
    },
    {
        "calculationDate": "20181009",
        "outstanding": 126050.0
    },
    {
        "calculationDate": "20181105",
        "outstanding": 124014.0
    },
    {
        "calculationDate": "20190902",
        "outstanding": 110761.0
    },
    {
        "calculationDate": "20171222",
        "outstanding": 20760.0
    },
    {
        "calculationDate": "20191010",
        "outstanding": 121931.0
    },
    {
        "calculationDate": "20180523",
        "outstanding": 39333.0
    },
    {
        "calculationDate": "20200903",
        "outstanding": 0.0
    },
    {
        "calculationDate": "20180920",
        "outstanding": 113203.0
    },
    {
        "calculationDate": "20180512",
        "outstanding": 10059.0
    },
    {
        "calculationDate": "20170710",
        "outstanding": 60159.0
    },
    {
        "calculationDate": "20200430",
        "outstanding": 54425.0
    },
    {
        "calculationDate": "20200813",
        "outstanding": 0.0
    },
    {
        "calculationDate": "20180307",
        "outstanding": 81813.0
    },
    {
        "calculationDate": "20200123",
        "outstanding": 145644.0
    },
    {
        "calculationDate": "20200130",
        "outstanding": 155644.0
    },
    {
        "calculationDate": "20201214",
        "outstanding": 0.0
    },
    {
        "calculationDate": "20181220",
        "outstanding": 121975.0
    },
    {
        "calculationDate": "20200227",
        "outstanding": 145521.0
    },
    {
        "calculationDate": "20180806",
        "outstanding": 111958.0
    },
    {
        "calculationDate": "20180525",
        "outstanding": 54806.0
    },
    {
        "calculationDate": "20190402",
        "outstanding": 124879.0
    },
    {
        "calculationDate": "20170818",
        "outstanding": 15000.0
    },
    {
        "calculationDate": "20190110",
        "outstanding": 123347.0
    },
    {
        "calculationDate": "20180906",
        "outstanding": 59092.0
    },
    {
        "calculationDate": "20190627",
        "outstanding": 100988.0
    },
    {
        "calculationDate": "20181122",
        "outstanding": 124011.0
    },
    {
        "calculationDate": "20190708",
        "outstanding": 92006.0
    },
    {
        "calculationDate": "20200601",
        "outstanding": 46509.0
    },
    {
        "calculationDate": "20200604",
        "outstanding": 39551.0
    },
    {
        "calculationDate": "20190801",
        "outstanding": 92506.0
    },
    {
        "calculationDate": "20200629",
        "outstanding": 40042.0
    },
    {
        "calculationDate": "20200824",
        "outstanding": 0.0
    },
    {
        "calculationDate": "20170918",
        "outstanding": 0.0
    },
    {
        "calculationDate": "20180215",
        "outstanding": 36719.0
    },
    {
        "calculationDate": "20180726",
        "outstanding": 110859.0
    },
    {
        "calculationDate": "20170525",
        "outstanding": 37549.0
    },
    {
        "calculationDate": "20201029",
        "outstanding": 49120.0
    },
    {
        "calculationDate": "20180328",
        "outstanding": 94316.0
    },
    {
        "calculationDate": "20180325",
        "outstanding": 94008.0
    },
    {
        "outstanding": 96073.0
    },
    {
        "calculationDate": "20170529",
        "outstanding": 42539.0
    },
    {
        "calculationDate": "20190829",
        "outstanding": 107990.0
    },
    {
        "calculationDate": "20180416",
        "outstanding": 102843.0
    },
    {
        "calculationDate": "20181227",
        "outstanding": 121975.0
    },
    {
        "calculationDate": "20200402",
        "outstanding": 89813.0
    },
    {
        "calculationDate": "20170629",
        "outstanding": 82438.0
    },
    {
        "calculationDate": "20191024",
        "outstanding": 133931.0
    },
    {
        "calculationDate": "20181011",
        "outstanding": 126050.0
    },
    {
        "calculationDate": "20190805",
        "outstanding": 92506.0
    },
    {
        "calculationDate": "20170803",
        "outstanding": 67588.0
    },
    {
        "calculationDate": "20200409",
        "outstanding": 97016.0
    },
    {
        "calculationDate": "20190103",
        "outstanding": 125883.0
    },
    {
        "calculationDate": "20170605",
        "outstanding": 48489.0
    },
    {
        "calculationDate": "20190411",
        "outstanding": 110401.0
    },
    {
        "calculationDate": "20180124",
        "outstanding": 20285.0
    },
    {
        "calculationDate": "20181206",
        "outstanding": 121526.0
    },
    {
        "calculationDate": "20170810",
        "outstanding": 10000.0
    },
    {
        "calculationDate": "20190507",
        "outstanding": 0.0
    },
    {
        "calculationDate": "20180531",
        "outstanding": 98673.0
    },
    {
        "calculationDate": "20180226",
        "outstanding": 64548.0
    },
    {
        "calculationDate": "20200416",
        "outstanding": 97016.0
    },
    {
        "calculationDate": "20200806",
        "outstanding": 23722.0
    },
    {
        "calculationDate": "20180823",
        "outstanding": 85324.0
    },
    {
        "calculationDate": "20180405",
        "outstanding": 110122.0
    },
    {
        "calculationDate": "20171010",
        "outstanding": 0.0
    },
    {
        "calculationDate": "20190430",
        "outstanding": 5507.0
    },
    {
        "calculationDate": "20180119",
        "outstanding": 17568.0
    },
    {
        "calculationDate": "20190221",
        "outstanding": 121497.0
    },
    {
        "calculationDate": "20180611",
        "outstanding": 114696.0
    },
    {
        "calculationDate": "20200716",
        "outstanding": 43544.0
    },
    {
        "calculationDate": "20200220",
        "outstanding": 135521.0
    },
    {
        "calculationDate": "20171109",
        "outstanding": 0.0
    },
    {
        "calculationDate": "20170508",
        "outstanding": 15514.0
    },
    {
        "calculationDate": "20170831",
        "outstanding": 37991.0
    },
    {
        "calculationDate": "20190606",
        "outstanding": 103988.0
    },
    {
        "calculationDate": "20201005",
        "outstanding": 50000.0
    },
    {
        "calculationDate": "20170706",
        "outstanding": 58192.0
    },
    {
        "calculationDate": "20191215",
        "outstanding": 116527.0
    },
    {
        "calculationDate": "20190503",
        "outstanding": 54827.0
    },
    {
        "calculationDate": "20200127",
        "outstanding": 145644.0
    },
    {
        "calculationDate": "20180308",
        "outstanding": 82683.0
    },
    {
        "calculationDate": "20180419",
        "outstanding": 105398.0
    },
    {
        "calculationDate": "20180108",
        "outstanding": 59.0
    },
    {
        "calculationDate": "20170703",
        "outstanding": 67725.0
    },
    {
        "calculationDate": "20200206",
        "outstanding": 130521.0
    },
    {
        "calculationDate": "20180607",
        "outstanding": 101212.0
    },
    {
        "calculationDate": "20180412",
        "outstanding": 98843.0
    },
    {
        "calculationDate": "20181012",
        "outstanding": 124014.0
    },
    {
        "calculationDate": "20200917",
        "outstanding": 50000.0
    },
    {
        "calculationDate": "20191017",
        "outstanding": 132931.0
    },
    {
        "calculationDate": "20170911",
        "outstanding": 0.0
    },
    {
        "calculationDate": "20170522",
        "outstanding": 32498.0
    },
    {
        "calculationDate": "20170608",
        "outstanding": 53390.0
    },
    {
        "calculationDate": "20190423",
        "outstanding": 120229.0
    },
    {
        "calculationDate": "20191208",
        "outstanding": 101527.0
    },
    {
        "calculationDate": "20180614",
        "outstanding": 115875.0
    },
    {
        "calculationDate": "20200326",
        "outstanding": 150891.0
    },
    {
        "calculationDate": "20180426",
        "outstanding": 95019.0
    },
    {
        "calculationDate": "20180625",
        "outstanding": 114875.0
    },
    {
        "calculationDate": "20191226",
        "outstanding": 116527.0
    },
    {
        "calculationDate": "20191003",
        "outstanding": 131363.0
    },
    {
        "calculationDate": "20181126",
        "outstanding": 124312.0
    },
    {
        "calculationDate": "20200423",
        "outstanding": 102016.0
    },
    {
        "calculationDate": "20200907",
        "outstanding": 50000.0
    },
    {
        "calculationDate": "20190329",
        "outstanding": 124351.0
    },
    {
        "calculationDate": "20200116",
        "outstanding": 125644.0
    },
    {
        "calculationDate": "20180115",
        "outstanding": 15059.0
    },
    {
        "calculationDate": "20190418",
        "outstanding": 119969.0
    },
    {
        "calculationDate": "20180816",
        "outstanding": 85104.0
    },
    {
        "calculationDate": "20200309",
        "outstanding": 150891.0
    },
    {
        "calculationDate": "20190124",
        "outstanding": 124145.0
    },
    {
        "calculationDate": "20201008",
        "outstanding": 49120.0
    },
    {
        "calculationDate": "20190305",
        "outstanding": 99731.0
    },
    {
        "calculationDate": "20170424",
        "outstanding": 19125.0
    },
    {
        "calculationDate": "20191110",
        "outstanding": 104677.0
    },
    {
        "calculationDate": "20190923",
        "outstanding": 121783.0
    },
    {
        "calculationDate": "20200810",
        "outstanding": 23722.0
    },
    {
        "calculationDate": "20200507",
        "outstanding": 45372.0
    },
    {
        "calculationDate": "20180112",
        "outstanding": 10059.0
    },
    {
        "calculationDate": "20180628",
        "outstanding": 114875.0
    },
    {
        "calculationDate": "20170601",
        "outstanding": 55293.0
    },
    {
        "calculationDate": "20200727",
        "outstanding": 44544.0
    },
    {
        "calculationDate": "20180430",
        "outstanding": 97126.0
    },
    {
        "calculationDate": "20181108",
        "outstanding": 123462.0
    },
    {
        "calculationDate": "20180911",
        "outstanding": 109151.0
    },
    {
        "calculationDate": "20180321",
        "outstanding": 85190.0
    },
    {
        "calculationDate": "20190415",
        "outstanding": 111929.0
    },
    {
        "calculationDate": "20170406",
        "outstanding": 0.0
    },
    {
        "calculationDate": "20190808",
        "outstanding": 93438.0
    },
    {
        "calculationDate": "20171214",
        "outstanding": 0.0
    },
    {
        "calculationDate": "20180318",
        "outstanding": 79149.0
    },
    {
        "calculationDate": "20190207",
        "outstanding": 119918.0
    },
    {
        "calculationDate": "20180904",
        "outstanding": 58515.0
    },
    {
        "calculationDate": "20190822",
        "outstanding": 101990.0
    },
    {
        "calculationDate": "20180621",
        "outstanding": 114875.0
    },
    {
        "calculationDate": "20191117",
        "outstanding": 105177.0
    },
    {
        "calculationDate": "20180205",
        "outstanding": 0.0
    },
    {
        "calculationDate": "20181231",
        "outstanding": 122818.0
    },
    {
        "calculationDate": "20180311",
        "outstanding": 77423.0
    },
    {
        "calculationDate": "20170717",
        "outstanding": 72482.0
    },
    {
        "calculationDate": "20200113",
        "outstanding": 110644.0
    },
    {
        "calculationDate": "20200204",
        "outstanding": 158640.0
    },
    {
        "calculationDate": "20190514",
        "outstanding": 50000.0
    },
    {
        "calculationDate": "20190222",
        "outstanding": 121497.0
    },
    {
        "calculationDate": "20170721",
        "outstanding": 76623.0
    },
    {
        "calculationDate": "20200730",
        "outstanding": 47544.0
    },
    {
        "calculationDate": "20200303",
        "outstanding": 148747.0
    },
    {
        "calculationDate": "20170907",
        "outstanding": 37008.0
    },
    {
        "calculationDate": "20170622",
        "outstanding": 73262.0
    },
    {
        "calculationDate": "20170518",
        "outstanding": 27640.0
    },
    {
        "calculationDate": "20200706",
        "outstanding": 34544.0
    },
    {
        "calculationDate": "20170713",
        "outstanding": 63131.0
    },
    {
        "calculationDate": "20200608",
        "outstanding": 40042.0
    },
    {
        "calculationDate": "20180223",
        "outstanding": 43320.0
    },
    {
        "calculationDate": "20200528",
        "outstanding": 45372.0
    },
    {
        "calculationDate": "20200427",
        "outstanding": 53925.0
    },
    {
        "calculationDate": "20180830",
        "outstanding": 48166.0
    },
    {
        "calculationDate": "20170619",
        "outstanding": 69751.0
    }
]