[
    {
        "calculationDate": "20220101",
        "outstanding": 198.23
    },
    {
        "calculationDate": "20211126",
        "outstanding": 1.0
    },
    {
        "calculationDate": "20211001",
        "outstanding": 0.05
    },
    {
        "calculationDate": "20220201",
        "outstanding": 198.23
    },
    {
        "calculationDate": "20220617",
        "outstanding": 0.0
    },
    {
        "calculationDate": "20211012",
        "outstanding": 1.0
    },
    {
        "calculationDate": "20230102",
        "outstanding": 0.0
    },
    {
        "calculationDate": "20220506",
        "outstanding": 0.0
    },
    {
        "calculationDate": "20221003",
        "outstanding": 199.0
    },
    {
        "calculationDate": "20220701",
        "outstanding": 198.36
    },
    {
        "calculationDate": "20230601",
        "outstanding": 0.0
    },
    {
        "calculationDate": "20220404",
        "outstanding": 0.0
    },
    {
        "calculationDate": "20220509",
        "outstanding": 0.0
    },
    {
        "calculationDate": "20220202",
        "outstanding": 199.0
    },
    {
        "calculationDate": "20220603",
        "outstanding": 198.0
    },
    {
        "calculationDate": "20211203",
        "outstanding": 199.0
    },
    {
        "calculationDate": "20210901",
        "outstanding": 0.0
    },
    {
        "calculationDate": "20220401",
        "outstanding": 0.0
    },
    {
        "calculationDate": "20220502",
        "outstanding": 199.0
    },
    {
        "calculationDate": "20221019",
        "outstanding": 0.0
    },
    {
        "calculationDate": "20220817",
        "outstanding": 0.0
    },
    {
        "calculationDate": "20220901",
        "outstanding": 198.0
    },
    {
        "calculationDate": "20220801",
        "outstanding": 199.0
    },
    {
        "calculationDate": "20221001",
        "outstanding": 199.0
    },
    {
        "calculationDate": "20220601",
        "outstanding": 197.36
    },
    {
        "calculationDate": "20230201",
        "outstanding": 0.0
    },
    {
        "calculationDate": "20220725",
        "outstanding": 0.0
    },
    {
        "calculationDate": "20220301",
        "outstanding": 198.23
    },
    {
        "calculationDate": "20220501",
        "outstanding": 198.36
    },
    {
        "calculationDate": "20221101",
        "outstanding": 197.37
    },
    {
        "calculationDate": "20220318",
        "outstanding": 0.0
    },
    {
        "calculationDate": "20230505",
        "outstanding": 0.0
    },
    {
        "calculationDate": "20220215",
        "outstanding": 0.0
    },
    {
        "calculationDate": "20221016",
        "outstanding": 58.37
    },
    {
        "calculationDate": "20210910",
        "outstanding": 1.0
    },
    {
        "calculationDate": "20230401",
        "outstanding": 0.0
    },
    {
        "calculationDate": "20211201",
        "outstanding": 198.98
    },
    {
        "calculationDate": "20211216",
        "outstanding": 0.07
    },
    {
        "calculationDate": "20220105",
        "outstanding": 199.0
    },
    {
        "calculationDate": "20220909",
        "outstanding": 0.0
    },
    {
        "calculationDate": "20220912",
        "outstanding": 0.0
    },
    {
        "calculationDate": "20221201",
        "outstanding": 198.37
    },
    {
        "calculationDate": "20211101",
        "outstanding": 0.0
    },
    {
        "calculationDate": "20230301",
        "outstanding": 180.11
    },
    {
        "calculationDate": "20220702",
        "outstanding": 0.0
    },
    {
        "calculationDate": "20220803",
        "outstanding": 199.0
    },
    {
        "calculationDate": "20221115",
        "outstanding": 0.0
    },
    {
        "calculationDate": "20230302",
        "outstanding": 0.0
    },
    {
        "calculationDate": "20220115",
        "outstanding": 0.04
    },
    {
        "calculationDate": "20221211",
        "outstanding": 0.0
    },
    {
        "calculationDate": "20220704",
        "outstanding": 0.0
    },
    {
        "calculationDate": "20220815",
        "outstanding": 0.0
    },
    {
        "calculationDate": "20210902",
        "outstanding": 0.1
    },
    {
        "calculationDate": "20220615",
        "outstanding": 0.0
    },
    {
        "calculationDate": "20220711",
        "outstanding": 0.0
    },
    {
        "calculationDate": "20220902",
        "outstanding": 198.0
    },
    {
        "calculationDate": "20230101",
        "outstanding": 172.77
    },
    {
        "calculationDate": "20230501",
        "outstanding": 176.68
    },
    {
        "calculationDate": "20220214",
        "outstanding": 0.0
    },
    {
        "calculationDate": "20220316",
        "outstanding": 0.0
    },
    {
        "calculationDate": "20211103",
        "outstanding": 0.0
    },
    {
        "calculationDate": "20220302",
        "outstanding": 199.0
    },
    {
        "calculationDate": "20221017",
        "outstanding": 59.0
    }
]